<?xml version="1.0" encoding="UTF-8"?>

-<VirtualDJ_Database Version="8.0.0">


-<Song Flag="64" FileSize="125389392" FilePath="D:\Musics\america\---Chris Brown, Tyga - Ayo (Explicit).mp4">

<Tags Flag="1" Remix="Explicit"/>

<Infos Cover="2" Bitrate="2784" FirstSeen="1549225844" SongLength="360.373333"/>

</Song>


-<Song Flag="64" FileSize="17451266" FilePath="D:\Musics\New 2017\Kamusungu Sungu Karitas Kario New Ugandan Music Video 2017.mp4">

<Tags Flag="1"/>

<Infos Cover="2" Bitrate="739" FirstSeen="1544978658" SongLength="188.940000"/>

</Song>


-<Song Flag="64" FileSize="26637952" FilePath="D:\Musics\New 2017\Ntaho Tuzajya by Ama G The Black New Rwandan Music Video 2017.mp4">

<Tags Flag="1"/>

<Infos Cover="2" Bitrate="737" FirstSeen="1544978658" SongLength="289.133333"/>

</Song>


-<Song Flag="64" FileSize="4500425" FilePath="D:\Musics\New 2017\Bruce Melodie yisanze yatamaje Amag the Black,amena amabanga.mp4">

<Tags Flag="1"/>

<Infos Cover="2" Bitrate="434" FirstSeen="1544978658" SongLength="82.895000"/>

</Song>


-<Song Flag="64" FileSize="3360976" FilePath="D:\Musics\New 2017\Byarara Bibaye by Marina New Rwandan Music 2017 BCMG YouTube.mp4">

<Tags Flag="1"/>

<Infos Cover="2" Bitrate="145" FirstSeen="1544978658" SongLength="185.225000"/>

</Song>


-<Song Flag="64" FileSize="12654669" FilePath="D:\Musics\New 2017\GGG.mp4">

<Tags Flag="1"/>

<Infos Cover="2" Bitrate="492" FirstSeen="1544978658" SongLength="205.611667"/>

</Song>


-<Song Flag="64" FileSize="12333301" FilePath="D:\Musics\New 2017\Khaligraph_3A_Complete_me__28Cover_29_-_Coke_Studio_Africa.mp4">

<Tags Flag="1"/>

<Infos Cover="2" Bitrate="712" FirstSeen="1544978658" SongLength="138.576667"/>

</Song>


-<Song Flag="64" FileSize="18347224" FilePath="D:\Musics\New 2017\Patoranking - Love you Die [Official Video] ft. Diamond Platnumz.mp4">

<Tags Flag="1" Remix="Official Video"/>

<Infos Cover="2" Bitrate="620" FirstSeen="1544978658" SongLength="236.610000"/>

</Song>


-<Song Flag="64" FileSize="14527077" FilePath="D:\Musics\New 2017\Imyambarire, imibyinire ya Marina yarangaje Abasore muri People's Club.mp4">

<Tags Flag="1"/>

<Infos Cover="2" Bitrate="734" FirstSeen="1544978658" SongLength="158.266667"/>

</Song>


-<Song Flag="64" FileSize="5945953" FilePath="D:\Musics\New 2017\VID-20170831-WA0011.mp4">

<Tags Flag="1"/>

<Infos Cover="2" Bitrate="223" FirstSeen="1544978658" SongLength="213.136000"/>

</Song>


-<Song Flag="64" FileSize="10076923" FilePath="D:\Musics\New 2017\VID-20170816-WA0054.mp4">

<Tags Flag="1"/>

<Infos Cover="2" Bitrate="223" FirstSeen="1544978658" SongLength="361.059000"/>

</Song>


-<Song Flag="64" FileSize="4240377" FilePath="D:\Musics\New 2017\VID-20170829-WA0005.mp4">

<Tags Flag="1"/>

<Infos Cover="2" Bitrate="142" FirstSeen="1544978658" SongLength="239.536667"/>

</Song>


-<Song Flag="64" FileSize="28651884" FilePath="D:\Musics\New 2017\lyrics of i m the one.mp4">

<Tags Flag="1"/>

<Infos Cover="2" Bitrate="784" FirstSeen="1544978658" SongLength="292.339229"/>

</Song>


-<Song Flag="64" FileSize="14515070" FilePath="D:\Musics\New 2017\KARABAYE! MARINA YAKOZE IBIDAKORWA KU RUBYINIRO YEREKANA IGITSINA CYE IMBERE Y'A.mp4">

<Tags Flag="1"/>

<Infos Cover="2" Bitrate="734" FirstSeen="1544978658" SongLength="158.266667"/>

</Song>


-<Song Flag="64" FileSize="12504707" FilePath="D:\Musics\New 2017\Super Star by Social Mula.mp4">

<Tags Flag="1"/>

<Infos Cover="2" Bitrate="404" FirstSeen="1544978658" SongLength="247.663333"/>

</Song>


-<Song Flag="64" FileSize="19011377" FilePath="D:\Musics\New 2017\Umukadaff_ft_imagineshen.mp4">

<Tags Flag="1"/>

<Infos Cover="2" Bitrate="693" FirstSeen="1544978658" SongLength="219.543333"/>

</Song>


-<Song Flag="64" FileSize="8918176" FilePath="D:\Musics\New 2017\Masikini_by_Edouce_Softman.mp4">

<Tags Flag="1"/>

<Infos Cover="2" Bitrate="283" FirstSeen="1544978658" SongLength="252.145000"/>

</Song>


-<Song Flag="64" FileSize="17942671" FilePath="D:\Musics\New 2017\Guru - Problem (Official Video).mp4">

<Tags Flag="1" Remix="Official Video"/>

<Infos Cover="2" Bitrate="736" FirstSeen="1544978658" SongLength="195.046667"/>

</Song>


-<Song Flag="64" FileSize="82628263" FilePath="D:\Musics\New 2017\ooooooooooooooooooooooooooo.mp4">

<Tags Flag="1"/>

<Infos Cover="2" Bitrate="2658" FirstSeen="1544978658" SongLength="248.733000"/>

</Song>


-<Song Flag="64" FileSize="13360891" FilePath="D:\Musics\New 2017\IPFUNDO BY PROS (OFFICIAL VIDEO) 2017.mp4">

<Tags Flag="1" Remix="OFFICIAL VIDEO"/>

<Infos Cover="2" Bitrate="479" FirstSeen="1544978658" SongLength="223.026667"/>

</Song>


-<Song Flag="64" FileSize="11730475" FilePath="D:\Musics\New 2017\lil-g in ubuzima ft marina from video.mp4">

<Tags Flag="1"/>

<Infos Cover="2" Bitrate="393" FirstSeen="1544978658" SongLength="238.723333"/>

</Song>


-<Song Flag="64" FileSize="7909462" FilePath="D:\Musics\New 2017\Justin Bieber - Love Yourself Lyrics.mp4">

<Tags Flag="1"/>

<Infos Cover="2" Bitrate="273" FirstSeen="1544978658" SongLength="231.548333"/>

</Song>


-<Song Flag="64" FileSize="5356287" FilePath="D:\Musics\New 2017\Harmonize - Nishachoka ( Official Audio).mp4">

<Tags Flag="1" Remix="Official Audio"/>

<Infos Cover="2" Bitrate="197" FirstSeen="1544978658" SongLength="217.848333"/>

</Song>


-<Song Flag="64" FileSize="48140000" FilePath="D:\Musics\New 2017\Kid Ink - That's On You [Official Video].mp4">

<Tags Flag="1" Remix="Official Video"/>

<Infos Cover="2" Bitrate="1812" FirstSeen="1544978658" SongLength="212.555000"/>

</Song>


-<Song Flag="64" FileSize="3701341" FilePath="D:\Musics\New 2017\Tuza_by_Mukadaff__28prod.evydecks_29.mp4">

<Tags Flag="1"/>

<Infos Cover="2" Bitrate="144" FirstSeen="1544978658" SongLength="205.216667"/>

</Song>


-<Song Flag="64" FileSize="13793583" FilePath="D:\Musics\New 2017\Sweet love by Davis D (Official Video 2017).mp4">

<Tags Flag="1" Remix="Official Video 2017"/>

<Infos Cover="2" Bitrate="602" FirstSeen="1544978658" SongLength="183.413333"/>

</Song>


-<Song Flag="64" FileSize="18882780" FilePath="D:\Musics\New 2017\Jux - Wivu (Official Music Video)_Full-HD.mp4">

<Tags Flag="1" Remix="Official Music Video"/>

<Infos Cover="2" Bitrate="663" FirstSeen="1544978658" SongLength="227.840000"/>

</Song>


-<Song FileSize="3291008" FilePath="D:\Musics\New 2017\Kimpe by Ganza(Official audio 2016) - 128K MP3.mp3">

<Tags Flag="2"/>

<Infos FirstSeen="1544978658"/>

</Song>


-<Song Flag="64" FileSize="7475724" FilePath="D:\Musics\New 2017\Online Love By Active New Rwandan Music 2016.mp4">

<Tags Flag="1"/>

<Infos Cover="2" Bitrate="222" FirstSeen="1544978658" SongLength="269.491000"/>

</Song>


-<Song Flag="64" FileSize="18981577" FilePath="D:\Musics\New 2017\Biremewe - Priscillah (Official Lyric Video).mp4">

<Tags Flag="1" Remix="Official Lyric Video"/>

<Infos Cover="2" Bitrate="522" FirstSeen="1544978658" SongLength="290.736667"/>

</Song>


-<Song Flag="64" FileSize="14110326" FilePath="D:\Musics\New 2017\SLOW_MOTIN_by_Mukadaff_ft__Sean_brizz.mp4">

<Tags Flag="1"/>

<Infos Cover="2" Bitrate="637" FirstSeen="1544978658" SongLength="177.075000"/>

</Song>


-<Song Flag="64" FileSize="11303539" FilePath="D:\Musics\New 2017\Riderman_-_INYUGUTI_ya_R_(Lyrics_Video).mp4">

<Tags Flag="1" Remix="Lyrics Video"/>

<Infos Cover="2" Bitrate="357" FirstSeen="1544978658" SongLength="253.398333"/>

</Song>


-<Song Flag="64" FileSize="5097360" FilePath="D:\Musics\New 2017\For Some One BY Tuff Gangz (Official Audio 2017).mp4">

<Tags Flag="1" Remix="Official Audio 2017"/>

<Infos Cover="2" Bitrate="166" FirstSeen="1544978658" SongLength="245.063333"/>

</Song>


-<Song Flag="64" FileSize="5185756" FilePath="D:\Musics\New 2017\Karezi by Racine Ft Extra (New Rwandan Music)2017.mp4">

<Tags Flag="1" Remix="New Rwandan Music"/>

<Infos Cover="2" Bitrate="173" FirstSeen="1544978658" SongLength="240.233333"/>

</Song>


-<Song Flag="64" FileSize="25014523" FilePath="D:\Musics\New 2017\I am a Victor By Tonzi (Official Video Lyrics) 2017.mp4">

<Tags Flag="1" Remix="Official Video Lyrics"/>

<Infos Cover="2" Bitrate="681" FirstSeen="1544978658" SongLength="293.661667"/>

</Song>


-<Song Flag="64" FileSize="18624929" FilePath="D:\Musics\New 2017\TAYARI By Distar ft Mr Kagame (Official Video) 2017.mp4">

<Tags Flag="1" Remix="Official Video"/>

<Infos Cover="2" Bitrate="716" FirstSeen="1544978658" SongLength="208.166667"/>

</Song>


-<Song Flag="64" FileSize="20634916" FilePath="D:\Musics\New 2017\Chin_Bees_-_Kababaye__28Official_Music_Video_29.mp4">

<Tags Flag="1"/>

<Infos Cover="2" Bitrate="733" FirstSeen="1544978658" SongLength="225.256667"/>

</Song>


-<Song Flag="64" FileSize="100552433" FilePath="D:\Musics\New 2017\Dore umuntu w'agaciro Meddy yahuriye nawe i Nyamata.mp4">

<Tags Flag="1"/>

<Infos Cover="2" Bitrate="552" FirstSeen="1544978658" SongLength="1456.123333"/>

</Song>


-<Song Flag="64" FileSize="4533032" FilePath="D:\Musics\New 2017\I miss You by Urban Boyz ft Kitoko( Sample Video 2017).mp4">

<Tags Flag="1" Remix="Sample Video 2017"/>

<Infos Cover="2" Bitrate="714" FirstSeen="1544978658" SongLength="50.805000"/>

</Song>


-<Song Flag="64" FileSize="6720264" FilePath="D:\Musics\New 2017\MUKADAFF_RAP_CHANNEL_FT_FIREMAN_OFFICIAL_AUDIO_2017.mp4">

<Tags Flag="1"/>

<Infos Cover="2" Bitrate="292" FirstSeen="1544978658" SongLength="183.901667"/>

</Song>


-<Song Flag="64" FileSize="13267638" FilePath="D:\Musics\New 2017\Yaramaramaje by Leone Dile ft Bulldog Official Video 2017).mp4">

<Tags Flag="1"/>

<Infos Cover="2" Bitrate="544" FirstSeen="1544978658" SongLength="195.023333"/>

</Song>


-<Song Flag="64" FileSize="68910683" FilePath="D:\Musics\New 2017\Alikiba - Seduce Me (Official Music Video).mp4">

<Tags Flag="1" Remix="Official Music Video"/>

<Infos Cover="2" Bitrate="2733" FirstSeen="1544978658" SongLength="201.734604" PlayCount="1" LastPlay="1544978745" FirstPlay="1544978745"/>

<Scan Version="800" Key="Fm" Volume="1.041095" AltBpm="0.450023" Bpm="0.600023"/>

<Poi Type="beatgrid" Pos="3.296213"/>

<Poi Type="automix" Pos="0.156000" Point="realStart"/>

<Poi Type="automix" Pos="197.656000" Point="realEnd"/>

<Poi Type="automix" Pos="201.734943" Point="fadeEnd"/>

<Poi Type="automix" Pos="0.488345" Point="cutStart"/>

<Poi Type="automix" Pos="191.593651" Point="cutEnd"/>

</Song>


-<Song Flag="64" FileSize="19996769" FilePath="D:\Musics\New 2017\Bruce_Melodie_2C_Khaligraph_and_Dj_Maphorisa__3A_Don_E2_80_99t_Know__E2_80_93_Coke_Studio_Africa.mp4">

<Tags Flag="1"/>

<Infos Cover="2" Bitrate="720" FirstSeen="1544978658" SongLength="222.098521"/>

<Scan Version="800" Key="F" Volume="0.204407" AltBpm="0.882336" Bpm="0.588231"/>

<Poi Type="beatgrid" Pos="22.990747"/>

<Poi Type="automix" Pos="0.424000" Point="realStart"/>

<Poi Type="automix" Pos="221.942667" Point="realEnd"/>

<Poi Type="automix" Point="fadeStart"/>

<Poi Type="automix" Pos="222.098118" Point="fadeEnd"/>

</Song>


-<Song Flag="64" FileSize="52972764" FilePath="D:\Musics\New 2017\Ace Hood - Bugatti ft. Future, Rick Ross.mpg.mpg">

<Tags Flag="2"/>

<Infos Bitrate="1392" FirstSeen="1544978658" SongLength="304.535500" PlayCount="4" LastPlay="1547000714" FirstPlay="1545542379"/>

<Scan Version="800" Key="C#m" Volume="0.667272" AltBpm="0.687029" Bpm="0.458016"/>

<Poi Type="beatgrid" Pos="2.393696"/>

<Poi Type="automix" Pos="0.113333" Point="realStart"/>

<Poi Type="automix" Pos="292.121333" Point="realEnd"/>

<Poi Type="automix" Pos="304.534762" Point="fadeEnd"/>

<Poi Type="automix" Pos="3.541043" Point="cutStart"/>

<Poi Type="automix" Pos="289.114558" Point="cutEnd"/>

</Song>


-<Song Flag="64" FileSize="18212844" FilePath="D:\Musics\New 2017\Zahabu by Charly na Nina (Official Video 2017).mp4">

<Tags Flag="1" Remix="Official Video 2017"/>

<Infos Cover="2" Bitrate="720" FirstSeen="1544978658" SongLength="202.500875" PlayCount="2" LastPlay="1547000652" FirstPlay="1546297652"/>

<Scan Version="800" Key="A" Volume="1.372972" AltBpm="0.450000" Bpm="0.600000"/>

<Poi Type="beatgrid" Pos="1.047732"/>

<Poi Type="automix" Pos="1.037333" Point="realStart"/>

<Poi Type="automix" Pos="195.353333" Point="realEnd"/>

<Poi Type="automix" Pos="202.499751" Point="fadeEnd"/>

<Poi Type="automix" Pos="1.037642" Point="cutStart"/>

<Poi Type="automix" Pos="190.642358" Point="cutEnd"/>

<Poi Type="automix" Pos="1.047528" Point="tempoStart"/>

<Poi Type="automix" Pos="173.843107" Point="tempoEnd"/>

</Song>


-<Song Flag="64" FileSize="17972443" FilePath="D:\Musics\New 2017\G VAN -- KWAKO (I'm in love) {Official Video}.mp4">

<Tags Flag="1" Remix="I'm in love"/>

<Infos Cover="2" Bitrate="619" FirstSeen="1544978658" SongLength="232.338521" PlayCount="2" LastPlay="1547422147" FirstPlay="1546300937"/>

<Scan Version="800" Key="F" Volume="1.194173" AltBpm="0.681814" Bpm="0.545465"/>

<Poi Type="beatgrid" Pos="8.315941"/>

<Poi Type="automix" Pos="0.141333" Point="realStart"/>

<Poi Type="automix" Pos="229.417333" Point="realEnd"/>

<Poi Type="automix" Pos="232.338118" Point="fadeEnd"/>

<Poi Type="automix" Pos="8.863492" Point="cutStart"/>

<Poi Type="automix" Pos="224.863492" Point="cutEnd"/>

</Song>


-<Song Flag="64" FileSize="4926938" FilePath="D:\Musics\New 2017\Justin_Bieber_-_Despacito_(Lyrics)_ft._Luis_Fonsi,_Daddy_Yankee.mp4">

<Tags Flag="1" Remix="Lyrics"/>

<Infos Cover="2" Bitrate="187" FirstSeen="1544978658" SongLength="210.488542" PlayCount="1" LastPlay="1546301080" FirstPlay="1546301080"/>

<Scan Version="800" Key="C#" Volume="1.117948" AltBpm="0.486247" Bpm="0.654966"/>

<Poi Type="beatgrid" Pos="61.184650"/>

<Poi Type="automix" Pos="0.078667" Point="realStart"/>

<Poi Type="automix" Pos="209.901333" Point="realEnd"/>

<Poi Type="automix" Point="fadeStart"/>

<Poi Type="automix" Pos="210.488866" Point="fadeEnd"/>

<Poi Type="automix" Pos="62.489252" Point="cutStart"/>

<Poi Type="automix" Pos="208.778594" Point="cutEnd"/>

<Poi Type="automix" Pos="62.494263" Point="tempoStart"/>

</Song>


-<Song Flag="64" FileSize="50482081" FilePath="D:\Musics\New 2017\Wcb wasafi ft Diamond Platnumz & Mbosso & Lavalava - JIBEBE (Official Video).mp4">

<Tags Flag="1" Remix="Official Video"/>

<Infos Cover="2" Bitrate="1764" FirstSeen="1544978658" SongLength="228.971625" PlayCount="2" LastPlay="1547000905" FirstPlay="1546301213"/>

<Scan Version="800" Key="D#m" Volume="1.355336" AltBpm="0.728163" Bpm="0.582517"/>

<Poi Type="beatgrid" Pos="0.545646"/>

<Poi Type="automix" Pos="0.248000" Point="realStart"/>

<Poi Type="automix" Pos="227.224000" Point="realEnd"/>

<Poi Type="automix" Pos="228.971224" Point="fadeEnd"/>

<Poi Type="automix" Pos="0.246712" Point="cutStart"/>

<Poi Type="automix" Pos="222.485624" Point="cutEnd"/>

</Song>


-<Song Flag="64" FileSize="12826115" FilePath="D:\Musics\New 2017\Bruce_Melodie_3A_Yego__28Cover_29_-_Coke_Studio_Africa.mp4">

<Tags Flag="1"/>

<Infos Cover="2" Bitrate="716" FirstSeen="1544978658" SongLength="143.336437" PlayCount="1" LastPlay="1547000423" FirstPlay="1547000423"/>

<Scan Version="800" Key="F#m" Volume="0.244002" AltBpm="0.647506" Bpm="0.431667"/>

<Poi Type="beatgrid" Pos="26.212812"/>

<Poi Type="automix" Pos="0.352000" Point="realStart"/>

<Poi Type="automix" Pos="143.184000" Point="realEnd"/>

<Poi Type="automix" Point="fadeStart"/>

<Poi Type="automix" Pos="143.336032" Point="fadeEnd"/>

</Song>


-<Song Flag="64" FileSize="11087674" FilePath="D:\Musics\New 2017\Generous-44_ KUKAGALI _Official_video.mp4">

<Tags Flag="1"/>

<Infos Cover="2" Bitrate="689" FirstSeen="1544978658" SongLength="128.684646"/>

<Scan Version="800" Key="C#" Volume="1.000714" AltBpm="0.857143" Bpm="0.571429"/>

<Poi Type="beatgrid" Pos="16.675238"/>

<Poi Type="automix" Pos="0.385333" Point="realStart"/>

<Poi Type="automix" Pos="128.581333" Point="realEnd"/>

<Poi Type="automix" Pos="0.835918" Point="fadeStart"/>

<Poi Type="automix" Pos="128.682789" Point="fadeEnd"/>

<Poi Type="automix" Pos="18.392381" Point="cutStart"/>

<Poi Type="automix" Pos="123.533787" Point="cutEnd"/>

</Song>


-<Song Flag="64" FileSize="11455508" FilePath="D:\Musics\New 2017\Dotcom_By_Mr_Kagame_ft_Peace_28Official_Music_Video_29.mp4">

<Tags Flag="1"/>

<Infos Cover="2" Bitrate="531" FirstSeen="1544978658" SongLength="172.732896"/>

<Scan Version="800" Key="Dm" Volume="0.801690" AltBpm="0.900000" Bpm="0.600023"/>

<Poi Type="beatgrid" Pos="4.382222"/>

<Poi Type="automix" Pos="0.192000" Point="realStart"/>

<Poi Type="automix" Pos="171.414667" Point="realEnd"/>

<Poi Type="automix" Pos="172.731043" Point="fadeEnd"/>

<Poi Type="automix" Pos="14.568345" Point="cutStart"/>

<Poi Type="automix" Pos="167.574785" Point="cutEnd"/>

</Song>


-<Song Flag="64" FileSize="23337223" FilePath="D:\Musics\New 2017\Riderman-_KADAGE_Lyrics_Video.mp4">

<Tags Flag="1"/>

<Infos Cover="2" Bitrate="665" FirstSeen="1544978658" SongLength="280.798896"/>

<Scan Version="800" Key="F" Volume="0.949321" AltBpm="0.542177" Bpm="0.361451"/>

<Poi Type="beatgrid" Pos="10.694694"/>

<Poi Type="automix" Pos="0.094667" Point="realStart"/>

<Poi Type="automix" Pos="276.570667" Point="realEnd"/>

<Poi Type="automix" Pos="280.798163" Point="fadeEnd"/>

<Poi Type="automix" Pos="11.769615" Point="cutStart"/>

<Poi Type="automix" Pos="260.095420" Point="cutEnd"/>

</Song>


-<Song FileSize="7793002" FilePath="D:\Musics\New 2017\36. Rihanna & Kayne West & Paul McCartney - FourFiveSeconds.mp3">

<Tags Flag="1" Year="2015" Album="Billboard Hot 100 Singles Chart" Genre="Hot 100" Title="FourFiveSeconds" Author="Rihanna & Kayne West & Paul McCartney"/>

<Infos Cover="1" Bitrate="331" FirstSeen="1544978658" SongLength="188.368958" PlayCount="1" LastPlay="1547422810" FirstPlay="1547422810"/>

<Comment>Compiled by GloDLS</Comment>

<Scan Version="800" Key="D" Volume="1.130366" AltBpm="0.728322" Bpm="0.582653"/>

<Poi Type="beatgrid" Pos="1.489977"/>

<Poi Type="automix" Pos="0.357333" Point="realStart"/>

<Poi Type="automix" Pos="186.741333" Point="realEnd"/>

<Poi Type="automix" Point="fadeStart"/>

<Poi Type="automix" Pos="194.824830" Point="fadeEnd"/>

<Poi Type="automix" Pos="6.204807" Point="cutStart"/>

<Poi Type="automix" Pos="186.263220" Point="cutEnd"/>

</Song>


-<Song FileSize="3204493" FilePath="D:\Musics\New 2017\Wibagirwa-Vuba-by-Charly-Nina-www.ibyamamare.com_.mp3">

<Tags Flag="2"/>

<Infos Bitrate="128" FirstSeen="1544978658" SongLength="200.280458" PlayCount="1" LastPlay="1547422358" FirstPlay="1547422358"/>

<Scan Version="800" Key="Fm" Volume="1.293422" AltBpm="0.529410" Bpm="0.705896"/>

<Poi Type="beatgrid" Pos="11.919954"/>

<Poi Type="automix" Pos="0.110667" Point="realStart"/>

<Poi Type="automix" Pos="197.993333" Point="realEnd"/>

<Poi Type="automix" Pos="200.280068" Point="fadeEnd"/>

<Poi Type="automix" Pos="11.382857" Point="cutStart"/>

<Poi Type="automix" Pos="180.621497" Point="cutEnd"/>

<Poi Type="loop" Pos="45.290667" Size="4.000000" Num="-1" Name="Saved Loop"/>

</Song>


-<Song Flag="64" FileSize="59387234" FilePath="D:\Musics\america\Desiigner - Panda.mp4">

<Tags Flag="1"/>

<Infos Cover="2" Bitrate="1956" FirstSeen="1549225879" SongLength="242.880479" PlayCount="1" LastPlay="1549225930" FirstPlay="1549225930"/>

<Scan Version="800" Key="D#" Volume="1.075972" AltBpm="0.620091" Bpm="0.826780"/>

<Poi Type="beatgrid" Pos="37.024899"/>

<Poi Type="automix" Pos="0.052000" Point="realStart"/>

<Poi Type="automix" Pos="240.021333" Point="realEnd"/>

<Poi Type="automix" Point="fadeStart"/>

<Poi Type="automix" Pos="242.862562" Point="fadeEnd"/>

<Poi Type="automix" Pos="39.300499" Point="cutStart"/>

<Poi Type="automix" Pos="224.704580" Point="cutEnd"/>

</Song>

</VirtualDJ_Database>